analytics/__init__.py
analytics/client.py
analytics/consumer.py
analytics/request.py
analytics/utils.py
analytics/version.py
analytics/test/__init__.py
analytics/test/client.py
analytics/test/consumer.py
analytics/test/module.py
analytics/test/request.py
analytics/test/utils.py
astronomer_analytics-1.2.7.dist-info/DESCRIPTION.rst
astronomer_analytics-1.2.7.dist-info/METADATA
astronomer_analytics-1.2.7.dist-info/RECORD
astronomer_analytics-1.2.7.dist-info/WHEEL
astronomer_analytics-1.2.7.dist-info/metadata.json
astronomer_analytics-1.2.7.dist-info/top_level.txt
