Metadata-Version: 2.0
Name: astronomer-analytics
Version: 1.2.7
Summary: The hassle-free way to integrate analytics into any Python application.
Home-page: https://github.com/astronomerio/analytics-python
Author: Astronomer
Author-email: taylor@astronomer.io
License: MIT License
Keywords: analytics astronomer astronomerio
Platform: UNKNOWN
Classifier: Development Status :: 5 - Production/Stable
Classifier: Intended Audience :: Developers
Classifier: License :: OSI Approved :: MIT License
Classifier: Operating System :: OS Independent
Classifier: Programming Language :: Python
Classifier: Programming Language :: Python :: 2
Classifier: Programming Language :: Python :: 2.6
Classifier: Programming Language :: Python :: 2.7
Classifier: Programming Language :: Python :: 3
Classifier: Programming Language :: Python :: 3.2
Classifier: Programming Language :: Python :: 3.3
Classifier: Programming Language :: Python :: 3.4
Classifier: Programming Language :: Python :: 3.5
Requires-Dist: requests (<3.0,>=2.7)
Requires-Dist: six (>=1.5)
Requires-Dist: python-dateutil (>2.1)
